GitLabPy.py
GitLabPy-0.6.1.dist-info/METADATA
GitLabPy-0.6.1.dist-info/RECORD
GitLabPy-0.6.1.dist-info/WHEEL
GitLabPy-0.6.1.dist-info/top_level.txt
