Metadata-Version: 2.1
Name: GitLabPy
Version: 0.6.1
Summary: A Python module to sort GitLab's Webhooks
Home-page: https://github.com/shadez95/GitLabPy
Author: Dixon Begay
Author-email: dixonbegay@gmail.com
Maintainer: Dixon Begay
License: MIT
Keywords: gitlabpy
Platform: UNKNOWN
Classifier: Development Status :: 3 - Alpha
Classifier: Intended Audience :: Developers
Classifier: Topic :: Software Development
Classifier: Programming Language :: Python :: 3.5
